{
  "__inputs": [
    {
      "name": "DS_PROMETHEUS",
      "label": "Prometheus",
      "description": "Prometheus data source",
      "type": "datasource",
      "pluginId": "prometheus",
      "pluginName": "Prometheus"
    },
    {
      "name": "DS_LOKI",
      "label": "Loki",
      "description": "Loki log aggregation",
      "type": "datasource",
      "pluginId": "loki",
      "pluginName": "Loki"
    },
    {
      "name": "DS_JAEGER",
      "label": "Jaeger",
      "description": "Jaeger distributed tracing",
      "type": "datasource",
      "pluginId": "jaeger",
      "pluginName": "Jaeger"
    }
  ],
  "__elements": {},
  "__requires": [
    {
      "type": "grafana",
      "id": "grafana",
      "name": "Grafana",
      "version": "10.2.0"
    },
    {
      "type": "datasource",
      "id": "prometheus",
      "name": "Prometheus",
      "version": "1.0.0"
    },
    {
      "type": "datasource",
      "id": "loki",
      "name": "Loki",
      "version": "1.0.0"
    },
    {
      "type": "datasource",
      "id": "jaeger",
      "name": "Jaeger",
      "version": "1.0.0"
    }
  ],
  "annotations": {
    "list": [
      {
        "builtIn": 1,
        "datasource": { "type": "grafana", "uid": "-- Grafana --" },
        "enable": true,
        "hide": true,
        "iconColor": "rgba(0, 211, 255, 1)",
        "name": "Annotations & Alerts",
        "type": "dashboard"
      }
    ]
  },
  "description": "End-to-end observability: distributed tracing, structured logs, PostgreSQL query traces, Redis instrumentation",
  "editable": true,
  "fiscalYearStartMonth": 0,
  "graphTooltip": 1,
  "id": null,
  "links": [
    {
      "asDropdown": false,
      "icon": "external link",
      "includeVars": false,
      "keepTime": true,
      "tags": [],
      "targetBlank": true,
      "title": "Jaeger UI",
      "tooltip": "Open Jaeger trace browser",
      "type": "link",
      "url": "http://192.168.168.31:16686"
    }
  ],
  "panels": [
    {
      "collapsed": false,
      "gridPos": { "h": 1, "w": 24, "x": 0, "y": 0 },
      "id": 100,
      "title": "📊 Request Tracing Overview",
      "type": "row"
    },
    {
      "datasource": { "type": "prometheus", "uid": "${DS_PROMETHEUS}" },
      "fieldConfig": {
        "defaults": {
          "color": { "mode": "thresholds" },
          "mappings": [],
          "thresholds": {
            "mode": "absolute",
            "steps": [
              { "color": "green", "value": null },
              { "color": "yellow", "value": 50 },
              { "color": "red", "value": 100 }
            ]
          },
          "unit": "ms"
        },
        "overrides": []
      },
      "gridPos": { "h": 4, "w": 6, "x": 0, "y": 1 },
      "id": 1,
      "options": {
        "colorMode": "background",
        "graphMode": "none",
        "justifyMode": "auto",
        "orientation": "auto",
        "reduceOptions": { "calcs": ["lastNotNull"], "fields": "", "values": false },
        "textMode": "auto"
      },
      "title": "P99 Request Latency",
      "type": "stat",
      "targets": [
        {
          "datasource": { "type": "prometheus", "uid": "${DS_PROMETHEUS}" },
          "expr": "histogram_quantile(0.99, sum(rate(http_request_duration_seconds_bucket{job=~\"code-server|oauth2-proxy|caddy\"}[5m])) by (le)) * 1000",
          "legendFormat": "p99",
          "refId": "A"
        }
      ]
    },
    {
      "datasource": { "type": "prometheus", "uid": "${DS_PROMETHEUS}" },
      "fieldConfig": {
        "defaults": {
          "color": { "mode": "thresholds" },
          "mappings": [],
          "thresholds": {
            "mode": "absolute",
            "steps": [
              { "color": "green", "value": null },
              { "color": "yellow", "value": 0.01 },
              { "color": "red", "value": 0.05 }
            ]
          },
          "unit": "percentunit"
        }
      },
      "gridPos": { "h": 4, "w": 6, "x": 6, "y": 1 },
      "id": 2,
      "options": {
        "colorMode": "background",
        "graphMode": "none",
        "justifyMode": "auto",
        "orientation": "auto",
        "reduceOptions": { "calcs": ["lastNotNull"], "fields": "", "values": false },
        "textMode": "auto"
      },
      "title": "Error Rate",
      "type": "stat",
      "targets": [
        {
          "datasource": { "type": "prometheus", "uid": "${DS_PROMETHEUS}" },
          "expr": "sum(rate(http_requests_total{status=~\"5..\"}[5m])) / sum(rate(http_requests_total[5m]))",
          "legendFormat": "Error Rate",
          "refId": "A"
        }
      ]
    },
    {
      "datasource": { "type": "prometheus", "uid": "${DS_PROMETHEUS}" },
      "fieldConfig": {
        "defaults": {
          "color": { "mode": "thresholds" },
          "mappings": [],
          "thresholds": {
            "mode": "absolute",
            "steps": [
              { "color": "green", "value": null },
              { "color": "yellow", "value": 100 },
              { "color": "red", "value": 500 }
            ]
          },
          "unit": "reqps"
        }
      },
      "gridPos": { "h": 4, "w": 6, "x": 12, "y": 1 },
      "id": 3,
      "options": {
        "colorMode": "value",
        "graphMode": "area",
        "justifyMode": "auto",
        "orientation": "auto",
        "reduceOptions": { "calcs": ["lastNotNull"], "fields": "", "values": false },
        "textMode": "auto"
      },
      "title": "Request Rate (RPS)",
      "type": "stat",
      "targets": [
        {
          "datasource": { "type": "prometheus", "uid": "${DS_PROMETHEUS}" },
          "expr": "sum(rate(http_requests_total[5m]))",
          "legendFormat": "RPS",
          "refId": "A"
        }
      ]
    },
    {
      "datasource": { "type": "prometheus", "uid": "${DS_PROMETHEUS}" },
      "fieldConfig": {
        "defaults": {
          "color": { "mode": "thresholds" },
          "mappings": [
            { "options": { "0": { "text": "DOWN" } }, "type": "value" },
            { "options": { "1": { "text": "UP" } }, "type": "value" }
          ],
          "thresholds": {
            "mode": "absolute",
            "steps": [
              { "color": "red", "value": null },
              { "color": "green", "value": 1 }
            ]
          }
        }
      },
      "gridPos": { "h": 4, "w": 6, "x": 18, "y": 1 },
      "id": 4,
      "options": {
        "colorMode": "background",
        "graphMode": "none",
        "justifyMode": "auto",
        "orientation": "auto",
        "reduceOptions": { "calcs": ["lastNotNull"], "fields": "", "values": false },
        "textMode": "auto"
      },
      "title": "Jaeger Collector Status",
      "type": "stat",
      "targets": [
        {
          "datasource": { "type": "prometheus", "uid": "${DS_PROMETHEUS}" },
          "expr": "up{job=\"jaeger\"}",
          "legendFormat": "Jaeger",
          "refId": "A"
        }
      ]
    },
    {
      "datasource": { "type": "prometheus", "uid": "${DS_PROMETHEUS}" },
      "fieldConfig": {
        "defaults": {
          "color": { "mode": "palette-classic" },
          "custom": {
            "axisBorderShow": false,
            "axisCenteredZero": false,
            "axisColorMode": "text",
            "axisLabel": "Latency (ms)",
            "fillOpacity": 10,
            "gradientMode": "none",
            "hideFrom": { "legend": false, "tooltip": false, "viz": false },
            "lineWidth": 2,
            "pointSize": 5,
            "showPoints": "auto",
            "spanNulls": false
          },
          "unit": "ms"
        }
      },
      "gridPos": { "h": 8, "w": 12, "x": 0, "y": 5 },
      "id": 5,
      "options": {
        "legend": { "calcs": ["mean", "max"], "displayMode": "table", "placement": "bottom", "showLegend": true },
        "tooltip": { "mode": "multi", "sort": "none" }
      },
      "title": "Request Latency Percentiles (Caddy → Services)",
      "type": "timeseries",
      "targets": [
        {
          "datasource": { "type": "prometheus", "uid": "${DS_PROMETHEUS}" },
          "expr": "histogram_quantile(0.50, sum(rate(http_request_duration_seconds_bucket[5m])) by (le)) * 1000",
          "legendFormat": "p50",
          "refId": "A"
        },
        {
          "datasource": { "type": "prometheus", "uid": "${DS_PROMETHEUS}" },
          "expr": "histogram_quantile(0.95, sum(rate(http_request_duration_seconds_bucket[5m])) by (le)) * 1000",
          "legendFormat": "p95",
          "refId": "B"
        },
        {
          "datasource": { "type": "prometheus", "uid": "${DS_PROMETHEUS}" },
          "expr": "histogram_quantile(0.99, sum(rate(http_request_duration_seconds_bucket[5m])) by (le)) * 1000",
          "legendFormat": "p99",
          "refId": "C"
        }
      ]
    },
    {
      "datasource": { "type": "prometheus", "uid": "${DS_PROMETHEUS}" },
      "fieldConfig": {
        "defaults": {
          "color": { "mode": "palette-classic" },
          "custom": {
            "fillOpacity": 10,
            "lineWidth": 2
          },
          "unit": "reqps"
        }
      },
      "gridPos": { "h": 8, "w": 12, "x": 12, "y": 5 },
      "id": 6,
      "options": {
        "legend": { "calcs": ["mean", "last"], "displayMode": "table", "placement": "bottom", "showLegend": true },
        "tooltip": { "mode": "multi", "sort": "none" }
      },
      "title": "Request Rate by Service",
      "type": "timeseries",
      "targets": [
        {
          "datasource": { "type": "prometheus", "uid": "${DS_PROMETHEUS}" },
          "expr": "sum(rate(http_requests_total[5m])) by (job)",
          "legendFormat": "{{job}}",
          "refId": "A"
        }
      ]
    },
    {
      "collapsed": false,
      "gridPos": { "h": 1, "w": 24, "x": 0, "y": 13 },
      "id": 200,
      "title": "🗃️ PostgreSQL Query Tracing",
      "type": "row"
    },
    {
      "datasource": { "type": "prometheus", "uid": "${DS_PROMETHEUS}" },
      "fieldConfig": {
        "defaults": {
          "color": { "mode": "palette-classic" },
          "custom": { "fillOpacity": 10, "lineWidth": 2 },
          "unit": "ms"
        }
      },
      "gridPos": { "h": 8, "w": 12, "x": 0, "y": 14 },
      "id": 10,
      "options": {
        "legend": { "calcs": ["mean", "max"], "displayMode": "table", "placement": "bottom", "showLegend": true },
        "tooltip": { "mode": "multi" }
      },
      "title": "PostgreSQL Query Latency (p50/p95/p99)",
      "type": "timeseries",
      "targets": [
        {
          "datasource": { "type": "prometheus", "uid": "${DS_PROMETHEUS}" },
          "expr": "histogram_quantile(0.50, sum(rate(pg_stat_statements_total_time_seconds_bucket[5m])) by (le)) * 1000",
          "legendFormat": "p50",
          "refId": "A"
        },
        {
          "datasource": { "type": "prometheus", "uid": "${DS_PROMETHEUS}" },
          "expr": "histogram_quantile(0.95, sum(rate(pg_stat_statements_total_time_seconds_bucket[5m])) by (le)) * 1000",
          "legendFormat": "p95",
          "refId": "B"
        },
        {
          "datasource": { "type": "prometheus", "uid": "${DS_PROMETHEUS}" },
          "expr": "histogram_quantile(0.99, sum(rate(pg_stat_statements_total_time_seconds_bucket[5m])) by (le)) * 1000",
          "legendFormat": "p99",
          "refId": "C"
        }
      ]
    },
    {
      "datasource": { "type": "prometheus", "uid": "${DS_PROMETHEUS}" },
      "fieldConfig": {
        "defaults": {
          "color": { "mode": "thresholds" },
          "mappings": [],
          "thresholds": {
            "mode": "absolute",
            "steps": [
              { "color": "red", "value": null },
              { "color": "yellow", "value": 0.95 },
              { "color": "green", "value": 0.99 }
            ]
          },
          "unit": "percentunit"
        }
      },
      "gridPos": { "h": 4, "w": 6, "x": 12, "y": 14 },
      "id": 11,
      "options": {
        "colorMode": "background",
        "graphMode": "area",
        "justifyMode": "auto",
        "orientation": "auto",
        "reduceOptions": { "calcs": ["lastNotNull"], "fields": "", "values": false },
        "textMode": "auto"
      },
      "title": "Cache Hit Ratio",
      "type": "stat",
      "targets": [
        {
          "datasource": { "type": "prometheus", "uid": "${DS_PROMETHEUS}" },
          "expr": "sum(pg_stat_database_blks_hit) / (sum(pg_stat_database_blks_hit) + sum(pg_stat_database_blks_read))",
          "legendFormat": "Cache Hit",
          "refId": "A"
        }
      ]
    },
    {
      "datasource": { "type": "prometheus", "uid": "${DS_PROMETHEUS}" },
      "fieldConfig": {
        "defaults": {
          "color": { "mode": "thresholds" },
          "thresholds": {
            "mode": "absolute",
            "steps": [
              { "color": "green", "value": null },
              { "color": "yellow", "value": 5 },
              { "color": "red", "value": 10 }
            ]
          },
          "unit": "short"
        }
      },
      "gridPos": { "h": 4, "w": 6, "x": 18, "y": 14 },
      "id": 12,
      "options": {
        "colorMode": "background",
        "graphMode": "none",
        "justifyMode": "auto",
        "orientation": "auto",
        "reduceOptions": { "calcs": ["lastNotNull"], "fields": "", "values": false },
        "textMode": "auto"
      },
      "title": "Active Locks",
      "type": "stat",
      "targets": [
        {
          "datasource": { "type": "prometheus", "uid": "${DS_PROMETHEUS}" },
          "expr": "pg_locks_count{mode=\"ExclusiveLock\"}",
          "legendFormat": "Exclusive Locks",
          "refId": "A"
        }
      ]
    },
    {
      "datasource": { "type": "prometheus", "uid": "${DS_PROMETHEUS}" },
      "fieldConfig": {
        "defaults": {
          "color": { "mode": "palette-classic" },
          "custom": { "fillOpacity": 10, "lineWidth": 2 },
          "unit": "short"
        }
      },
      "gridPos": { "h": 4, "w": 12, "x": 12, "y": 18 },
      "id": 13,
      "options": {
        "legend": { "calcs": ["last"], "displayMode": "list", "placement": "bottom", "showLegend": true },
        "tooltip": { "mode": "single" }
      },
      "title": "PostgreSQL Active Connections",
      "type": "timeseries",
      "targets": [
        {
          "datasource": { "type": "prometheus", "uid": "${DS_PROMETHEUS}" },
          "expr": "pg_stat_activity_count{state=\"active\"}",
          "legendFormat": "Active",
          "refId": "A"
        },
        {
          "datasource": { "type": "prometheus", "uid": "${DS_PROMETHEUS}" },
          "expr": "pg_stat_activity_count{state=\"idle\"}",
          "legendFormat": "Idle",
          "refId": "B"
        }
      ]
    },
    {
      "collapsed": false,
      "gridPos": { "h": 1, "w": 24, "x": 0, "y": 22 },
      "id": 300,
      "title": "⚡ Redis Cache Instrumentation",
      "type": "row"
    },
    {
      "datasource": { "type": "prometheus", "uid": "${DS_PROMETHEUS}" },
      "fieldConfig": {
        "defaults": {
          "color": { "mode": "thresholds" },
          "thresholds": {
            "mode": "absolute",
            "steps": [
              { "color": "red", "value": null },
              { "color": "yellow", "value": 0.7 },
              { "color": "green", "value": 0.85 }
            ]
          },
          "unit": "percentunit"
        }
      },
      "gridPos": { "h": 4, "w": 6, "x": 0, "y": 23 },
      "id": 20,
      "options": {
        "colorMode": "background",
        "graphMode": "area",
        "justifyMode": "auto",
        "orientation": "auto",
        "reduceOptions": { "calcs": ["lastNotNull"], "fields": "", "values": false },
        "textMode": "auto"
      },
      "title": "Redis Cache Hit Rate",
      "type": "stat",
      "targets": [
        {
          "datasource": { "type": "prometheus", "uid": "${DS_PROMETHEUS}" },
          "expr": "redis_keyspace_hits_total / (redis_keyspace_hits_total + redis_keyspace_misses_total)",
          "legendFormat": "Hit Rate",
          "refId": "A"
        }
      ]
    },
    {
      "datasource": { "type": "prometheus", "uid": "${DS_PROMETHEUS}" },
      "fieldConfig": {
        "defaults": {
          "color": { "mode": "thresholds" },
          "thresholds": {
            "mode": "absolute",
            "steps": [
              { "color": "green", "value": null },
              { "color": "yellow", "value": 400000000 },
              { "color": "red", "value": 450000000 }
            ]
          },
          "unit": "bytes"
        }
      },
      "gridPos": { "h": 4, "w": 6, "x": 6, "y": 23 },
      "id": 21,
      "options": {
        "colorMode": "value",
        "graphMode": "area",
        "justifyMode": "auto",
        "orientation": "auto",
        "reduceOptions": { "calcs": ["lastNotNull"], "fields": "", "values": false },
        "textMode": "auto"
      },
      "title": "Redis Memory Used",
      "type": "stat",
      "targets": [
        {
          "datasource": { "type": "prometheus", "uid": "${DS_PROMETHEUS}" },
          "expr": "redis_memory_used_bytes",
          "legendFormat": "Memory Used",
          "refId": "A"
        }
      ]
    },
    {
      "datasource": { "type": "prometheus", "uid": "${DS_PROMETHEUS}" },
      "fieldConfig": {
        "defaults": {
          "color": { "mode": "palette-classic" },
          "custom": { "fillOpacity": 10, "lineWidth": 2 },
          "unit": "ms"
        }
      },
      "gridPos": { "h": 8, "w": 12, "x": 0, "y": 27 },
      "id": 22,
      "options": {
        "legend": { "calcs": ["mean", "max"], "displayMode": "table", "placement": "bottom", "showLegend": true },
        "tooltip": { "mode": "multi" }
      },
      "title": "Redis Operation Latency (p50/p95/p99)",
      "type": "timeseries",
      "targets": [
        {
          "datasource": { "type": "prometheus", "uid": "${DS_PROMETHEUS}" },
          "expr": "histogram_quantile(0.50, sum(rate(redis_command_duration_seconds_bucket[5m])) by (le)) * 1000",
          "legendFormat": "p50",
          "refId": "A"
        },
        {
          "datasource": { "type": "prometheus", "uid": "${DS_PROMETHEUS}" },
          "expr": "histogram_quantile(0.95, sum(rate(redis_command_duration_seconds_bucket[5m])) by (le)) * 1000",
          "legendFormat": "p95",
          "refId": "B"
        },
        {
          "datasource": { "type": "prometheus", "uid": "${DS_PROMETHEUS}" },
          "expr": "histogram_quantile(0.99, sum(rate(redis_command_duration_seconds_bucket[5m])) by (le)) * 1000",
          "legendFormat": "p99",
          "refId": "C"
        }
      ]
    },
    {
      "datasource": { "type": "prometheus", "uid": "${DS_PROMETHEUS}" },
      "fieldConfig": {
        "defaults": {
          "color": { "mode": "palette-classic" },
          "custom": { "fillOpacity": 10, "lineWidth": 2 },
          "unit": "ops"
        }
      },
      "gridPos": { "h": 8, "w": 12, "x": 12, "y": 27 },
      "id": 23,
      "options": {
        "legend": { "calcs": ["mean", "last"], "displayMode": "table", "placement": "bottom", "showLegend": true },
        "tooltip": { "mode": "multi" }
      },
      "title": "Redis Commands Rate by Type",
      "type": "timeseries",
      "targets": [
        {
          "datasource": { "type": "prometheus", "uid": "${DS_PROMETHEUS}" },
          "expr": "sum(rate(redis_commands_processed_total[5m])) by (cmd)",
          "legendFormat": "{{cmd}}",
          "refId": "A"
        }
      ]
    },
    {
      "collapsed": false,
      "gridPos": { "h": 1, "w": 24, "x": 0, "y": 35 },
      "id": 400,
      "title": "📋 Structured Logs (Loki)",
      "type": "row"
    },
    {
      "datasource": { "type": "loki", "uid": "${DS_LOKI}" },
      "fieldConfig": {
        "defaults": {
          "color": { "mode": "palette-classic" },
          "custom": { "fillOpacity": 10, "lineWidth": 2 }
        }
      },
      "gridPos": { "h": 6, "w": 12, "x": 0, "y": 36 },
      "id": 30,
      "options": {
        "dedupStrategy": "none",
        "enableLogDetails": true,
        "prettifyLogMessage": true,
        "showTime": true,
        "showCommonLabels": false,
        "sortOrder": "Descending",
        "wrapLogMessage": false
      },
      "title": "Recent Error Logs",
      "type": "logs",
      "targets": [
        {
          "datasource": { "type": "loki", "uid": "${DS_LOKI}" },
          "expr": "{app=~\"code-server|oauth2-proxy|caddy\"} |= \"error\" | json | level=\"error\"",
          "legendFormat": "",
          "refId": "A"
        }
      ]
    },
    {
      "datasource": { "type": "loki", "uid": "${DS_LOKI}" },
      "fieldConfig": {
        "defaults": {
          "color": { "mode": "palette-classic" },
          "custom": { "fillOpacity": 10, "lineWidth": 2 }
        }
      },
      "gridPos": { "h": 6, "w": 12, "x": 12, "y": 36 },
      "id": 31,
      "options": {
        "dedupStrategy": "none",
        "enableLogDetails": true,
        "prettifyLogMessage": true,
        "showTime": true,
        "showCommonLabels": false,
        "sortOrder": "Descending",
        "wrapLogMessage": false
      },
      "title": "Slow Query Logs (>100ms)",
      "type": "logs",
      "targets": [
        {
          "datasource": { "type": "loki", "uid": "${DS_LOKI}" },
          "expr": "{app=\"postgres\"} |= \"duration\" | regexp `duration: (?P<duration>[\\d.]+) ms` | duration > 100",
          "legendFormat": "",
          "refId": "A"
        }
      ]
    },
    {
      "collapsed": false,
      "gridPos": { "h": 1, "w": 24, "x": 0, "y": 42 },
      "id": 500,
      "title": "🔍 Distributed Trace Correlations",
      "type": "row"
    },
    {
      "datasource": { "type": "prometheus", "uid": "${DS_PROMETHEUS}" },
      "fieldConfig": {
        "defaults": {
          "color": { "mode": "palette-classic" },
          "custom": { "fillOpacity": 5, "lineWidth": 2 },
          "unit": "short"
        }
      },
      "gridPos": { "h": 8, "w": 12, "x": 0, "y": 43 },
      "id": 40,
      "options": {
        "legend": { "calcs": ["sum"], "displayMode": "table", "placement": "bottom", "showLegend": true },
        "tooltip": { "mode": "multi" }
      },
      "title": "Trace Spans by Service",
      "type": "timeseries",
      "targets": [
        {
          "datasource": { "type": "prometheus", "uid": "${DS_PROMETHEUS}" },
          "expr": "sum(rate(jaeger_tracer_spans_total[5m])) by (service)",
          "legendFormat": "{{service}}",
          "refId": "A"
        }
      ]
    },
    {
      "datasource": { "type": "prometheus", "uid": "${DS_PROMETHEUS}" },
      "fieldConfig": {
        "defaults": {
          "color": { "mode": "palette-classic" },
          "custom": { "fillOpacity": 5, "lineWidth": 2 },
          "unit": "short"
        }
      },
      "gridPos": { "h": 8, "w": 12, "x": 12, "y": 43 },
      "id": 41,
      "options": {
        "legend": { "calcs": ["last"], "displayMode": "table", "placement": "bottom", "showLegend": true },
        "tooltip": { "mode": "multi" }
      },
      "title": "Trace Error Rate by Service",
      "type": "timeseries",
      "targets": [
        {
          "datasource": { "type": "prometheus", "uid": "${DS_PROMETHEUS}" },
          "expr": "sum(rate(jaeger_tracer_spans_total{result=\"err\"}[5m])) by (service) / sum(rate(jaeger_tracer_spans_total[5m])) by (service)",
          "legendFormat": "{{service}} error rate",
          "refId": "A"
        }
      ]
    }
  ],
  "refresh": "30s",
  "schemaVersion": 38,
  "tags": ["observability", "tracing", "telemetry", "phase-3", "production"],
  "templating": {
    "list": [
      {
        "current": {},
        "datasource": { "type": "prometheus", "uid": "${DS_PROMETHEUS}" },
        "definition": "label_values(up, instance)",
        "hide": 0,
        "includeAll": true,
        "multi": true,
        "name": "instance",
        "options": [],
        "query": { "query": "label_values(up, instance)", "refId": "StandardVariableQuery" },
        "refresh": 2,
        "regex": "",
        "sort": 1,
        "type": "query",
        "label": "Instance"
      }
    ]
  },
  "time": { "from": "now-1h", "to": "now" },
  "timepicker": {},
  "timezone": "browser",
  "title": "Observability Spine — Tracing, Logs, PostgreSQL, Redis",
  "uid": "observability-spine-v1",
  "version": 1
}
